docs/__init__.py
docs/conf.py
pythreatmatrix/__init__.py
pythreatmatrix/exceptions.py
pythreatmatrix/main.py
pythreatmatrix/pythreatmatrix.py
pythreatmatrix/version.py
pythreatmatrix/cli/__init__.py
pythreatmatrix/cli/_jobs_utils.py
pythreatmatrix/cli/_utils.py
pythreatmatrix/cli/analyse.py
pythreatmatrix/cli/commands.py
pythreatmatrix/cli/config.py
pythreatmatrix/cli/domain_checkers.py
pythreatmatrix/cli/jobs.py
pythreatmatrix/cli/tags.py
tests/__init__.py
tests/mocked_requests.py
tests/test_general.py
tests/test_jobs.py
tests/test_tags.py
tests/utils.py
pythreatmatrix-5.0.0.dist-info/LICENSE
pythreatmatrix-5.0.0.dist-info/METADATA
pythreatmatrix-5.0.0.dist-info/WHEEL
pythreatmatrix-5.0.0.dist-info/entry_points.txt
pythreatmatrix-5.0.0.dist-info/top_level.txt
pythreatmatrix-5.0.0.dist-info/RECORD
