Metadata-Version: 2.1
Name: pythreatmatrix
Version: 5.0.0
Summary: Robust Python SDK and CLI for ThreatMatrix's API
Home-page: https://github.com/khulnasoft/pythreatmatrix
Author: Matteo Lodi
Project-URL: Documentation, https://github.com/khulnasoft/pythreatmatrix
Project-URL: Funding, https://liberapay.com/KhulnaSoft/
Project-URL: Source, https://github.com/khulnasoft/pythreatmatrix
Project-URL: Tracker, https://github.com/khulnasoft/pythreatmatrix/issues
Keywords: threatmatrix sdk python command line osint threat intel malware
Classifier: Development Status :: 5 - Production/Stable
Classifier: Intended Audience :: Developers
Classifier: Environment :: Web Environment
Classifier: License :: OSI Approved :: GNU Affero General Public License v3 or later (AGPLv3+)
Classifier: Programming Language :: Python :: 3.8
Classifier: Programming Language :: Python :: 3.9
Classifier: Programming Language :: Python :: 3.10
Classifier: Topic :: Software Development :: Libraries :: Python Modules
Requires-Python: >=3.8
License-File: LICENSE
Requires-Dist: requests >=2.28
Requires-Dist: geocoder >=1.38
Requires-Dist: click >=7.0
Requires-Dist: rich >=12.5.1
Requires-Dist: click-creds >=0.0.3
Requires-Dist: typing-extensions >=4.3.0
Provides-Extra: dev
Requires-Dist: black ==22.3.0 ; extra == 'dev'
Requires-Dist: flake8 ==4.0.1 ; extra == 'dev'
Requires-Dist: isort ==5.10.1 ; extra == 'dev'
Requires-Dist: pre-commit ==2.17.0 ; extra == 'dev'
Requires-Dist: tox ==3.25.1 ; extra == 'dev'
Requires-Dist: tox-gh-actions ==2.9.1 ; extra == 'dev'
Requires-Dist: codecov ==2.1.13 ; extra == 'dev'
Requires-Dist: requests >=2.28 ; extra == 'dev'
Requires-Dist: geocoder >=1.38 ; extra == 'dev'
Requires-Dist: click >=7.0 ; extra == 'dev'
Requires-Dist: rich >=12.5.1 ; extra == 'dev'
Requires-Dist: click-creds >=0.0.3 ; extra == 'dev'
Requires-Dist: typing-extensions >=4.3.0 ; extra == 'dev'
Provides-Extra: test
Requires-Dist: black ==22.3.0 ; extra == 'test'
Requires-Dist: flake8 ==4.0.1 ; extra == 'test'
Requires-Dist: isort ==5.10.1 ; extra == 'test'
Requires-Dist: pre-commit ==2.17.0 ; extra == 'test'
Requires-Dist: tox ==3.25.1 ; extra == 'test'
Requires-Dist: tox-gh-actions ==2.9.1 ; extra == 'test'
Requires-Dist: codecov ==2.1.13 ; extra == 'test'
Requires-Dist: requests >=2.28 ; extra == 'test'
Requires-Dist: geocoder >=1.38 ; extra == 'test'
Requires-Dist: click >=7.0 ; extra == 'test'
Requires-Dist: rich >=12.5.1 ; extra == 'test'
Requires-Dist: click-creds >=0.0.3 ; extra == 'test'
Requires-Dist: typing-extensions >=4.3.0 ; extra == 'test'
